MANIFEST.in
README.rst
setup.py
bin/gyun
bin/gyun.cmd
bin/gyun_completer
gyun/__init__.py
gyun/cli/__init__.py
gyun/cli/completer.py
gyun/cli/driver.py
gyun/cli/iaas_client/__init__.py
gyun/cli/iaas_client/handler.py
gyun/cli/iaas_client/actions/__init__.py
gyun/cli/iaas_client/actions/base.py
gyun/cli/iaas_client/actions/alarm_policy/__init__.py
gyun/cli/iaas_client/actions/alarm_policy/describe_alarm_policies.py
gyun/cli/iaas_client/actions/dns_alias/__init__.py
gyun/cli/iaas_client/actions/dns_alias/associate_dns_alias.py
gyun/cli/iaas_client/actions/dns_alias/describe_dns_aliases.py
gyun/cli/iaas_client/actions/dns_alias/dissociate_dns_aliases.py
gyun/cli/iaas_client/actions/dns_alias/get_dns_label.py
gyun/cli/iaas_client/actions/eip/__init__.py
gyun/cli/iaas_client/actions/eip/allocate_eips.py
gyun/cli/iaas_client/actions/eip/associate_eip.py
gyun/cli/iaas_client/actions/eip/change_eips_bandwidth.py
gyun/cli/iaas_client/actions/eip/change_eips_billing_mode.py
gyun/cli/iaas_client/actions/eip/describe_eips.py
gyun/cli/iaas_client/actions/eip/dissociate_eips.py
gyun/cli/iaas_client/actions/eip/modify_eip_attributes.py
gyun/cli/iaas_client/actions/eip/release_eips.py
gyun/cli/iaas_client/actions/image/__init__.py
gyun/cli/iaas_client/actions/image/capture_instance.py
gyun/cli/iaas_client/actions/image/delete_images.py
gyun/cli/iaas_client/actions/image/describe_images.py
gyun/cli/iaas_client/actions/image/modify_image_attributes.py
gyun/cli/iaas_client/actions/instance/__init__.py
gyun/cli/iaas_client/actions/instance/describe_instances.py
gyun/cli/iaas_client/actions/instance/modify_instance_attributes.py
gyun/cli/iaas_client/actions/instance/reset_instances.py
gyun/cli/iaas_client/actions/instance/resize_instances.py
gyun/cli/iaas_client/actions/instance/restart_instances.py
gyun/cli/iaas_client/actions/instance/run_instances.py
gyun/cli/iaas_client/actions/instance/start_instances.py
gyun/cli/iaas_client/actions/instance/stop_instances.py
gyun_cli.egg-info/PKG-INFO
gyun_cli.egg-info/SOURCES.txt
gyun_cli.egg-info/dependency_links.txt
gyun_cli.egg-info/namespace_packages.txt
gyun_cli.egg-info/requires.txt
gyun_cli.egg-info/top_level.txt