Metadata-Version: 1.0
Name: gyun-cli
Version: 1.2
Summary: Command Line Interface for GYUN.
Home-page: http://docs.qc.gyun.com
Author: GYUN Team
Author-email: service@gomeholdings.com
License: UNKNOWN
Keywords: gyun iaas gomestor cli
Platform: UNKNOWN
